odoo/addons/contract_sale_generation/README.rst
odoo/addons/contract_sale_generation/__init__.py
odoo/addons/contract_sale_generation/__manifest__.py
odoo/addons/contract_sale_generation/data/contract_cron.xml
odoo/addons/contract_sale_generation/i18n/ca.po
odoo/addons/contract_sale_generation/i18n/contract_sale_generation.pot
odoo/addons/contract_sale_generation/i18n/de.po
odoo/addons/contract_sale_generation/i18n/el_GR.po
odoo/addons/contract_sale_generation/i18n/es.po
odoo/addons/contract_sale_generation/i18n/es_AR.po
odoo/addons/contract_sale_generation/i18n/es_MX.po
odoo/addons/contract_sale_generation/i18n/fi.po
odoo/addons/contract_sale_generation/i18n/fr.po
odoo/addons/contract_sale_generation/i18n/gl.po
odoo/addons/contract_sale_generation/i18n/hi_IN.po
odoo/addons/contract_sale_generation/i18n/hr.po
odoo/addons/contract_sale_generation/i18n/hr_HR.po
odoo/addons/contract_sale_generation/i18n/hu.po
odoo/addons/contract_sale_generation/i18n/it.po
odoo/addons/contract_sale_generation/i18n/nl.po
odoo/addons/contract_sale_generation/i18n/nl_NL.po
odoo/addons/contract_sale_generation/i18n/pt.po
odoo/addons/contract_sale_generation/i18n/pt_BR.po
odoo/addons/contract_sale_generation/i18n/pt_PT.po
odoo/addons/contract_sale_generation/i18n/ro.po
odoo/addons/contract_sale_generation/i18n/ru.po
odoo/addons/contract_sale_generation/i18n/sk_SK.po
odoo/addons/contract_sale_generation/i18n/sl.po
odoo/addons/contract_sale_generation/i18n/tr.po
odoo/addons/contract_sale_generation/i18n/tr_TR.po
odoo/addons/contract_sale_generation/i18n/zh_CN.po
odoo/addons/contract_sale_generation/models/__init__.py
odoo/addons/contract_sale_generation/models/abstract_contract.py
odoo/addons/contract_sale_generation/models/contract.py
odoo/addons/contract_sale_generation/models/contract_line.py
odoo/addons/contract_sale_generation/models/sale_order.py
odoo/addons/contract_sale_generation/models/sale_order_line.py
odoo/addons/contract_sale_generation/readme/CONTRIBUTORS.rst
odoo14_addon_contract_sale_generation-14.0.1.0.2.dist-info/METADATA
odoo14_addon_contract_sale_generation-14.0.1.0.2.dist-info/WHEEL
odoo14_addon_contract_sale_generation-14.0.1.0.2.dist-info/top_level.txt
odoo14_addon_contract_sale_generation-14.0.1.0.2.dist-info/RECORD
